[{"name":"render_template.action_view","payload":{"identifier":"/Users/jp/SpotifyApp/app/views/home/index.html.haml","layout":"layouts/application"},"time":"2019-10-03T11:21:14.950+01:00","transaction_id":"17de2334ca689ce72365","end":"2019-10-03T11:21:14.965+01:00","children":[],"duration":14.539},{"name":"process_action.action_controller","payload":{"controller":"HomeController","action":"index","params":{"controller":"home","action":"index"},"headers":{"SCRIPT_NAME":"","QUERY_STRING":"","SERVER_PROTOCOL":"HTTP/1.1","SERVER_SOFTWARE":"puma 3.12.1 Llamas in Pajamas","GATEWAY_INTERFACE":"CGI/1.2","REQUEST_METHOD":"GET","REQUEST_PATH":"/","REQUEST_URI":"/","HTTP_VERSION":"HTTP/1.1","HTTP_HOST":"localhost:3000","HTTP_CONNECTION":"keep-alive","HTTP_CACHE_CONTROL":"max-age=0","HTTP_UPGRADE_INSECURE_REQUESTS":"1","HTTP_USER_AGENT":"Mozilla/5.0 (Macintosh; Intel Mac OS X 10_14_5) AppleWebKit/537.36 (KHTML, like Gecko) Chrome/77.0.3865.90 Safari/537.36","HTTP_SEC_FETCH_MODE":"navigate","HTTP_SEC_FETCH_USER":"?1","HTTP_ACCEPT":"text/html,application/xhtml+xml,application/xml;q=0.9,image/webp,image/apng,*/*;q=0.8,application/signed-exchange;v=b3","HTTP_SEC_FETCH_SITE":"none","HTTP_ACCEPT_ENCODING":"gzip, deflate, br","HTTP_ACCEPT_LANGUAGE":"en-GB,en-US;q=0.9,en;q=0.8","HTTP_COOKIE":"_ga=GA1.1.465737510.1561547915; hubspotutk=8c3dc8a2adadbf3f3b2f8feb8ef653bb; _hjid=98fbc25e-7e42-4762-8262-130a0ceedba0; __hstc=181257784.8c3dc8a2adadbf3f3b2f8feb8ef653bb.1561547915311.1567717993695.1567787725844.78; _myapp_session=d%2FTz8jQ8Mt9DnUi2tcRjSgtw5L4TVRTwBZSltRbZdiWSVXrPRCNO4rTjUG9wOIlhNG%2FCPsLZ6zOgd%2B8nz8SeMuPOuLNpRRJauwRB5NdNe3xQGxAB6HTOvSZmzGDiVx4Oz2wWCFF75QDZEtWApr4%3D--dC%2BSLB%2B5Bms6mzO%2F--NHbxDiCfI%2FfFq%2F3rAySofg%3D%3D","HTTP_IF_NONE_MATCH":"W/\"4ff85897836fcc4e341b6d42146cb8b4\"","SERVER_NAME":"localhost","SERVER_PORT":"3000","PATH_INFO":"/","REMOTE_ADDR":"::1","ROUTES_70134145073080_SCRIPT_NAME":"","ORIGINAL_FULLPATH":"/","ORIGINAL_SCRIPT_NAME":""},"format":"html","method":"GET","path":"/","status":200,"view_runtime":347.08400000818074,"db_runtime":0},"time":"2019-10-03T11:21:14.942+01:00","transaction_id":"17de2334ca689ce72365","end":"2019-10-03T11:21:15.292+01:00","children":[],"duration":350.385}]