[{"name":"render_template.action_view","payload":{"identifier":"/Users/jp/SpotifyApp/app/views/home/index.html.haml","layout":"layouts/application"},"time":"2019-10-04T15:27:46.591+01:00","transaction_id":"91af2c99bda847ddc716","end":"2019-10-04T15:27:46.602+01:00","children":[],"duration":11.243},{"name":"process_action.action_controller","payload":{"controller":"HomeController","action":"index","params":{"controller":"home","action":"index"},"headers":{"SCRIPT_NAME":"","QUERY_STRING":"","SERVER_PROTOCOL":"HTTP/1.1","SERVER_SOFTWARE":"puma 3.12.1 Llamas in Pajamas","GATEWAY_INTERFACE":"CGI/1.2","REQUEST_METHOD":"GET","REQUEST_PATH":"/","REQUEST_URI":"/","HTTP_VERSION":"HTTP/1.1","HTTP_HOST":"localhost:3000","HTTP_CONNECTION":"keep-alive","HTTP_UPGRADE_INSECURE_REQUESTS":"1","HTTP_USER_AGENT":"Mozilla/5.0 (Macintosh; Intel Mac OS X 10_14_5) AppleWebKit/537.36 (KHTML, like Gecko) Chrome/77.0.3865.90 Safari/537.36","HTTP_SEC_FETCH_MODE":"navigate","HTTP_SEC_FETCH_USER":"?1","HTTP_ACCEPT":"text/html,application/xhtml+xml,application/xml;q=0.9,image/webp,image/apng,*/*;q=0.8,application/signed-exchange;v=b3","HTTP_PURPOSE":"prefetch","HTTP_SEC_FETCH_SITE":"none","HTTP_ACCEPT_ENCODING":"gzip, deflate, br","HTTP_ACCEPT_LANGUAGE":"en-GB,en-US;q=0.9,en;q=0.8","HTTP_COOKIE":"_ga=GA1.1.465737510.1561547915; hubspotutk=8c3dc8a2adadbf3f3b2f8feb8ef653bb; _hjid=98fbc25e-7e42-4762-8262-130a0ceedba0; __hstc=181257784.8c3dc8a2adadbf3f3b2f8feb8ef653bb.1561547915311.1567717993695.1567787725844.78; _myapp_session=iA9RmIWH%2FfjCptbmpqF5%2BhG%2FvGICc23T5QYAU6yCvqs03k0t23F0Dm%2BGL8nIdg3VQlsCFDJ1%2B9H0VD%2B9eJSb6%2FLHgTimXy33%2F6RKrkp9nTwZ%2BVjW%2BwTi2TFtjmSzXysue3ik2VjKTqaoZmZtqHM%3D--5pijqp3wouuvG%2FYx--hvA2N5RVCpXHlEBiFEuKFw%3D%3D","HTTP_IF_NONE_MATCH":"W/\"077214d83c96ea82e4037f23e4661604\"","SERVER_NAME":"localhost","SERVER_PORT":"3000","PATH_INFO":"/","REMOTE_ADDR":"::1","ROUTES_70334542436000_SCRIPT_NAME":"","ORIGINAL_FULLPATH":"/","ORIGINAL_SCRIPT_NAME":""},"format":"html","method":"GET","path":"/","status":200,"view_runtime":4526.39299997827,"db_runtime":0},"time":"2019-10-04T15:27:46.579+01:00","transaction_id":"91af2c99bda847ddc716","end":"2019-10-04T15:27:51.111+01:00","children":[],"duration":4531.912}]